control/__init__.py
control/cli.py
control/commech.py
control/commmech.py
control/controller.py
control/router.py
control/test.py
control/version.py
control/xenstore.py
unimon_ctl-0.0.1.dist-info/LICENSE
unimon_ctl-0.0.1.dist-info/METADATA
unimon_ctl-0.0.1.dist-info/WHEEL
unimon_ctl-0.0.1.dist-info/entry_points.txt
unimon_ctl-0.0.1.dist-info/top_level.txt
unimon_ctl-0.0.1.dist-info/RECORD
