Metadata-Version: 2.1
Name: unimon-ctl
Version: 0.0.1
Summary: Control ClickOS Domains (and get unimon data)
Home-page: https://github.com/willfantom/unimon-ctl
Author: Will Fantom
Author-email: w.fantom@lancaster.ac.uk
License: UNKNOWN
Keywords: unikernel clickos unimon
Platform: UNKNOWN
Classifier: Programming Language :: Python
Classifier: License :: OSI Approved :: GNU General Public License v3 (GPLv3)
Classifier: Operating System :: Unix
Requires-Dist: pyxs
